flanellograf/__init__.py
flanellograf/__main__.py
flanellograf/utils.py
flanellograf-0.4.2.dist-info/licenses/LICENSE
flanellograf-0.4.2.dist-info/WHEEL
flanellograf-0.4.2.dist-info/METADATA
flanellograf-0.4.2.dist-info/RECORD
