Metadata-Version: 2.4
Name: flanellograf
Version: 0.4.2
Summary: Tool for making presentations using the Python REPL
Keywords: presentation,repl,code,documentation
Author: Sondre S. Ødegård
Requires-Python: >=3.9
Classifier: License :: OSI Approved :: MIT License
Classifier: Topic :: Documentation
Classifier: Topic :: Education
License-File: LICENSE
Requires-Dist: rich
Requires-Dist: black ; extra == "dev"
Requires-Dist: isort ; extra == "dev"
Requires-Dist: flit ; extra == "dev"
Project-URL: Documentation, https://github.com/sondreod/flanellograf
Project-URL: Source, https://github.com/sondreod/flanellograf
Provides-Extra: dev
